{"name":"eks-mcp","actions":{"CallPrivilegedTool":{"conditionKeys":[],"resources":[],"description":"Grants permission to call privileged tools in MCP service","accessLevel":"Write","resourceTypes":[],"url":"https://docs.aws.amazon.com/eks/latest/userguide/eks-mcp-tool-configurations.html"},"CallReadOnlyTool":{"conditionKeys":[],"resources":[],"description":"Grants permission to call read-only tools in MCP service","accessLevel":"Read","resourceTypes":[],"url":"https://docs.aws.amazon.com/eks/latest/userguide/eks-mcp-tool-configurations.html"},"InvokeMcp":{"conditionKeys":[],"resources":[],"description":"Grants permission to use MCP service","accessLevel":"Read","resourceTypes":[],"url":"https://docs.aws.amazon.com/eks/latest/userguide/eks-mcp-tool-configurations.html"}},"resources":[],"conditionKeys":{},"url":"https://docs.aws.amazon.com/service-authorization/latest/reference/list_amazoneksmcpserver.html"}